syncnet/__init__.py
syncnet/channel.py
syncnet/endpoint.py
syncnet/listener.py
syncnet/server.py
syncnet-1.0.0.dist-info/METADATA
syncnet-1.0.0.dist-info/WHEEL
syncnet-1.0.0.dist-info/top_level.txt
syncnet-1.0.0.dist-info/RECORD
