Metadata-Version: 2.4
Name: syncnet
Version: 1.0.0
Summary: A ligthweight multiplayer networking library for games
Author-email: Jomari Tenorio <jtenorio.dev@gmail.com>
License: MIT
Classifier: Development Status :: 3 - Alpha
Classifier: Intended Audience :: Developers
Classifier: Programming Language :: Python :: 3.12
Requires-Python: >=3.12
